rest_framework_nimbus/LICENSE.txt
rest_framework_nimbus/__init__.py
rest_framework_nimbus/admin.py
rest_framework_nimbus/admintools.py
rest_framework_nimbus/apps.py
rest_framework_nimbus/code.py
rest_framework_nimbus/constants.py
rest_framework_nimbus/err_code.py
rest_framework_nimbus/exceptions.py
rest_framework_nimbus/fields.py
rest_framework_nimbus/filters.py
rest_framework_nimbus/manager.py
rest_framework_nimbus/models.py
rest_framework_nimbus/parsers.py
rest_framework_nimbus/permissions.py
rest_framework_nimbus/serializers.py
rest_framework_nimbus/settings.py
rest_framework_nimbus/tests.py
rest_framework_nimbus/throttling.py
rest_framework_nimbus/urls.py
rest_framework_nimbus/validators.py
rest_framework_nimbus/versioning.py
rest_framework_nimbus/widgets.py
rest_framework_nimbus/authentication/__init__.py
rest_framework_nimbus/authentication/auth_jwt.py
rest_framework_nimbus/authentication/auth_token.py
rest_framework_nimbus/authentication/auth_user.py
rest_framework_nimbus/consul/__init__.py
rest_framework_nimbus/consul/client.py
rest_framework_nimbus/handler/__init__.py
rest_framework_nimbus/handler/api.py
rest_framework_nimbus/jwt/__init__.py
rest_framework_nimbus/jwt/handler.py
rest_framework_nimbus/locale/en/LC_MESSAGES/django.po
rest_framework_nimbus/locale/zh/LC_MESSAGES/django.po
rest_framework_nimbus/migrations/__init__.py
rest_framework_nimbus/pagination/__init__.py
rest_framework_nimbus/pagination/base.py
rest_framework_nimbus/pagination/full.py
rest_framework_nimbus/renderers/__init__.py
rest_framework_nimbus/renderers/api.py
rest_framework_nimbus/renderers/base.py
rest_framework_nimbus/static/nimbus/css/filter.css
rest_framework_nimbus/static/nimbus/js/filter.js
rest_framework_nimbus/utils/__init__.py
rest_framework_nimbus/utils/api.py
rest_framework_nimbus/utils/base.py
rest_framework_nimbus/utils/des.py
rest_framework_nimbus/utils/menu.py
rest_framework_nimbus/utils/utility.py
rest_framework_nimbus/views/__init__.py
djangorestframework_nimbus-4.4.6.dist-info/LICENSE.md
djangorestframework_nimbus-4.4.6.dist-info/METADATA
djangorestframework_nimbus-4.4.6.dist-info/WHEEL
djangorestframework_nimbus-4.4.6.dist-info/top_level.txt
djangorestframework_nimbus-4.4.6.dist-info/RECORD
