Metadata-Version: 2.1
Name: djangorestframework-nimbus
Version: 4.4.6
Summary: djangorestframework-nimbus
Home-page: https://github.com/williamren
Author: william
Author-email: william.ren@live.cn
License: Apache License 2.0
Keywords: rest_framework_nimbus,nimbus,django,api
Platform: Any
Classifier: Development Status :: 5 - Production/Stable
Classifier: Intended Audience :: Developers
Classifier: License :: OSI Approved :: Apache Software License
Classifier: Operating System :: MacOS :: MacOS X
Classifier: Operating System :: Microsoft :: Windows
Classifier: Operating System :: POSIX
Classifier: Programming Language :: Python
Classifier: Programming Language :: Python :: 3
Classifier: Programming Language :: Python :: 3.7
Classifier: Programming Language :: Python :: 3.8
Classifier: Programming Language :: Python :: 3.9
Classifier: Programming Language :: Python :: 3.10
Classifier: Programming Language :: Python :: 3.11
Classifier: Topic :: Internet :: WWW/HTTP
Classifier: Environment :: Web Environment
Classifier: Framework :: Django
Classifier: Framework :: Django :: 4.0
License-File: LICENSE.md
Requires-Dist: Django
Requires-Dist: django-mptt
Requires-Dist: djangorestframework
Requires-Dist: djangorestframework-jwt
Requires-Dist: djangorestframework-recursive
Requires-Dist: python-dateutil
Requires-Dist: coreapi
Requires-Dist: nimbus-utils >=1.3.4
